poppt/__init__.py
poppt/api/__init__.py
poppt/api/ppt.py
poppt/core/PPTType.py
poppt/core/__init__.py
poppt/lib/__init__.py
poppt/lib/ppt/__init__.py
poppt/lib/ppt/ppt2pdf_service.py
tests/__init__.py
tests/test_ppt.py
poppt-0.1.1.dist-info/LICENSE
poppt-0.1.1.dist-info/METADATA
poppt-0.1.1.dist-info/WHEEL
poppt-0.1.1.dist-info/top_level.txt
poppt-0.1.1.dist-info/RECORD
