Metadata-Version: 2.1
Name: poppt
Version: 0.1.1
Summary: pip install poppt
Home-page: https://www.python-office.com/
Author: CoderWanFeng
Author-email: 1957875073@qq.com
License: MIT
Project-URL: Bug Tracker, https://github.com/CoderWanFeng/poppt/issues
Project-URL: Documentation, https://github.com/CoderWanFeng/poppt/blob/master/README.md
Project-URL: Source Code, https://github.com/CoderWanFeng/poppt
Platform: any
Requires-Python: >=3.7
License-File: LICENSE
Requires-Dist: pywin32
Requires-Dist: poprogress
Requires-Dist: pofile
Requires-Dist: pillow
